LICENCE.txt
MANIFEST.in
README.txt
setup.py
kumo_browser.egg-info/PKG-INFO
kumo_browser.egg-info/SOURCES.txt
kumo_browser.egg-info/dependency_links.txt
kumo_browser.egg-info/top_level.txt
kumobasicbrowser/__init__.py