Metadata-Version: 2.1
Name: kumo-browser
Version: 0.0.1
Summary: A Browser library which returns content of the web page from various different webpages
Home-page: 
Author: Kosta Jevtic
Author-email: kosta.jevtic@jobcloud.ch
License: MIT
Keywords: browser
Classifier: Development Status :: 5 - Production/Stable
Classifier: Intended Audience :: Education
Classifier: Operating System :: Microsoft :: Windows :: Windows 10
Classifier: License :: OSI Approved :: MIT License
Classifier: Programming Language :: Python :: 3
License-File: LICENCE.txt
